odoo/addons/web_notify_upgrade/README.rst
odoo/addons/web_notify_upgrade/__init__.py
odoo/addons/web_notify_upgrade/__manifest__.py
odoo/addons/web_notify_upgrade/i18n/fr.po
odoo/addons/web_notify_upgrade/i18n/it.po
odoo/addons/web_notify_upgrade/i18n/web_notify_upgrade.pot
odoo/addons/web_notify_upgrade/models/__init__.py
odoo/addons/web_notify_upgrade/models/ir_model.py
odoo/addons/web_notify_upgrade/readme/CONTRIBUTORS.md
odoo/addons/web_notify_upgrade/readme/DESCRIPTION.md
odoo/addons/web_notify_upgrade/static/description/icon.png
odoo/addons/web_notify_upgrade/static/description/index.html
odoo/addons/web_notify_upgrade/static/description/notify.png
odoo_addon_web_notify_upgrade-18.0.1.0.0.2.dist-info/METADATA
odoo_addon_web_notify_upgrade-18.0.1.0.0.2.dist-info/WHEEL
odoo_addon_web_notify_upgrade-18.0.1.0.0.2.dist-info/top_level.txt
odoo_addon_web_notify_upgrade-18.0.1.0.0.2.dist-info/RECORD
