Metadata-Version: 2.1
Name: odoo-addon-web_notify_upgrade
Version: 18.0.1.0.0.2
Requires-Python: >=3.10
Requires-Dist: odoo-addon-web_notify==18.0.*
Requires-Dist: odoo==18.0.*
Summary: Notify active users when a module is installed or updated
Home-page: https://github.com/OCA/web
License: AGPL-3
Author: Akretion, Odoo Community Association (OCA)
Author-email: support@odoo-community.org
Classifier: Programming Language :: Python
Classifier: Framework :: Odoo
Classifier: Framework :: Odoo :: 18.0
Classifier: License :: OSI Approved :: GNU Affero General Public License v3
